odoo/addons/account_timesheet_time_type/README.rst
odoo/addons/account_timesheet_time_type/__init__.py
odoo/addons/account_timesheet_time_type/__manifest__.py
odoo/addons/account_timesheet_time_type/static/description/icon.png
odoo/addons/account_timesheet_time_type/views/analytic_account_view.xml
odoo_addon_account_timesheet_time_type-16.0.1.0.0.1.dist-info/METADATA
odoo_addon_account_timesheet_time_type-16.0.1.0.0.1.dist-info/WHEEL
odoo_addon_account_timesheet_time_type-16.0.1.0.0.1.dist-info/top_level.txt
odoo_addon_account_timesheet_time_type-16.0.1.0.0.1.dist-info/RECORD
